scanner/__init__.py
scanner/scanner.py
look_like_scanned-1.0.8.dist-info/METADATA
look_like_scanned-1.0.8.dist-info/WHEEL
look_like_scanned-1.0.8.dist-info/entry_points.txt
look_like_scanned-1.0.8.dist-info/licenses/LICENSE
look_like_scanned-1.0.8.dist-info/RECORD
