Metadata-Version: 2.4
Name: look-like-scanned
Version: 1.0.8
Summary: Python script to make documents look like they were scanned.
License-File: LICENSE
Keywords: pdf,scan,scanner,image-to-pdf,pdf-to-scan,convert-pdf
Author: navchandar
Author-email: 12165092+navchandar@users.noreply.github.com
Requires-Python: >=3.8,<4.0
Classifier: Development Status :: 5 - Production/Stable
Classifier: Environment :: Console
Classifier: Intended Audience :: Developers
Classifier: Intended Audience :: End Users/Desktop
Classifier: Intended Audience :: Information Technology
Classifier: License :: OSI Approved :: MIT License
Classifier: Operating System :: Microsoft :: Windows
Classifier: Operating System :: Microsoft :: Windows :: Windows 10
Classifier: Operating System :: Microsoft :: Windows :: Windows 11
Classifier: Operating System :: OS Independent
Classifier: Operating System :: POSIX :: Linux
Classifier: Programming Language :: Python
Classifier: Programming Language :: Python :: 3
Classifier: Programming Language :: Python :: 3.8
Classifier: Programming Language :: Python :: 3.9
Classifier: Programming Language :: Python :: 3.10
Classifier: Programming Language :: Python :: 3.11
Classifier: Programming Language :: Python :: 3.12
Classifier: Programming Language :: Python :: 3.13
Classifier: Programming Language :: Python :: 3.14
Classifier: Topic :: Software Development :: Libraries :: Python Modules
Classifier: Topic :: Text Processing
Classifier: Topic :: Utilities
Requires-Dist: colorama (>=0.4.6,<0.5.0)
Requires-Dist: pillow (>=10.0.1,<11.0.0)
Requires-Dist: pypdfium2 (>=5.0.0,<6.0.0)
Project-URL: Bug Tracker, https://github.com/navchandar/look-like-scanned/issues
Project-URL: Funding, https://www.buymeacoffee.com/navchandar/
Project-URL: Homepage, https://navchandar.github.io/look-like-scanned/
Project-URL: Repository, https://github.com/navchandar/look-like-scanned
